bytristan/__init__.py
bytristan/bytristan.py
bytristan-0.4.dist-info/METADATA
bytristan-0.4.dist-info/WHEEL
bytristan-0.4.dist-info/top_level.txt
bytristan-0.4.dist-info/RECORD
