Metadata-Version: 2.1
Name: bytristan
Version: 0.4
Summary: A module for enforcing Tristan comments
Author: tristandev
